boolshit/__init__.py
boolshit/maybe.py
boolshit-1.0.0.dist-info/METADATA
boolshit-1.0.0.dist-info/WHEEL
boolshit-1.0.0.dist-info/top_level.txt
boolshit-1.0.0.dist-info/RECORD
