Metadata-Version: 2.1
Name: boolshit
Version: 1.0.0
Summary: https://github.com/hirsimaki-markus/boolshit
